prympt/__init__.py
prympt/exceptions.py
prympt/output.py
prympt/prompt.py
prympt/response.py
prympt-1.0.5.dist-info/LICENCE
prympt-1.0.5.dist-info/METADATA
prympt-1.0.5.dist-info/WHEEL
prympt-1.0.5.dist-info/top_level.txt
prympt-1.0.5.dist-info/RECORD
