Metadata-Version: 2.2
Name: prympt
Version: 1.0.5
Summary: A Python Package for LLM Prompting and Interfacing
Author-email: "foofaraw (GitHub: foofaraw)" <foofaraw.github@gmail.com>
Keywords: llm,prompt,ai
Classifier: License :: OSI Approved :: MIT License
Classifier: Programming Language :: Python
Classifier: Programming Language :: Python :: 3
Requires-Python: >=3.9
License-File: LICENCE
Requires-Dist: litellm>=0.3.0
Requires-Dist: jinja2>=3.1.2
Requires-Dist: lxml>=5.3.1
Provides-Extra: dev
Requires-Dist: pytest==8.3.4; extra == "dev"
Requires-Dist: pytest-cov==6.0.0; extra == "dev"
Requires-Dist: black==25.1.0; extra == "dev"
Requires-Dist: ruff==0.9.5; extra == "dev"
Requires-Dist: mypy==1.15.0; extra == "dev"
Requires-Dist: mypy-extensions==1.0.0; extra == "dev"
Requires-Dist: isort==6.0.0; extra == "dev"
Requires-Dist: pathspec==0.12.1; extra == "dev"
Requires-Dist: platformdirs==4.3.6; extra == "dev"
